file_saver/__init__.py
file_saver/api.py
file_saver/application.py
file_saver/get_event.py
file_saver/handler.py
file_saver/sample_events.py
file_saver/controllers/base_controller.py
file_saver/controllers/downloader_controller.py
file_saver/controllers/uploader_controller.py
file_saver/factories/base_factory.py
file_saver/factories/factory.py
file_saver/infra/compresser/zip_compresser.py
file_saver/infra/mongo_downloader/mongo_downloader.py
file_saver/infra/mongo_uploader/mongo_uploader.py
file_saver/models/request.py
file_saver/models/response.py
file_saver/services/base_service.py
file_saver/services/downloader_service.py
file_saver/services/uploader_service.py
file_saver/utils/file.py
file_saver/utils/helpers.py
file_saver/utils/html.py
file_saver/utils/json.py
file_saver/utils/lambda_helpers.py
file_saver/utils/markdown.py
file_saver/utils/string_utils.py
file_saver/utils/text.py
file_saver/utils/time.py
file_saver/utils/url.py
video_bot_mongo_file_saver-0.0.4.dist-info/LICENSE
video_bot_mongo_file_saver-0.0.4.dist-info/METADATA
video_bot_mongo_file_saver-0.0.4.dist-info/WHEEL
video_bot_mongo_file_saver-0.0.4.dist-info/top_level.txt
video_bot_mongo_file_saver-0.0.4.dist-info/RECORD
