Metadata-Version: 2.1
Name: video-bot-mongo-file-saver
Version: 0.0.4
Summary: Mongo File Saver module
Author-email: Bruno de Paula <bruno.bert.jj@gmail.com>
License: MIT License
Project-URL: Homepage, https://github.com/bruno-bert/microservice-mongo-file-saver
Keywords: file,saver,mongo,gridfs,storage
Classifier: Programming Language :: Python :: 3
Classifier: License :: OSI Approved :: MIT License
Classifier: Operating System :: OS Independent
Requires-Python: >=3.7
License-File: LICENSE
Requires-Dist: altgraph (==0.17.3)
Requires-Dist: aniso8601 (==9.0.1)
Requires-Dist: bleach (==5.0.1)
Requires-Dist: certifi (==2022.9.24)
Requires-Dist: cffi (==1.15.1)
Requires-Dist: charset-normalizer (==2.1.1)
Requires-Dist: click (==8.1.3)
Requires-Dist: coloredlogs (==15.0.1)
Requires-Dist: commonmark (==0.9.1)
Requires-Dist: cryptography (==38.0.3)
Requires-Dist: dnspython (==2.2.1)
Requires-Dist: docutils (==0.19)
Requires-Dist: Flask (==2.2.2)
Requires-Dist: Flask-PyMongo (==2.3.0)
Requires-Dist: Flask-RESTful (==0.3.9)
Requires-Dist: humanfriendly (==10.0)
Requires-Dist: idna (==3.4)
Requires-Dist: importlib-metadata (==5.0.0)
Requires-Dist: itsdangerous (==2.1.2)
Requires-Dist: jaraco.classes (==3.2.3)
Requires-Dist: jeepney (==0.8.0)
Requires-Dist: Jinja2 (==3.1.2)
Requires-Dist: keyring (==23.11.0)
Requires-Dist: MarkupSafe (==2.1.1)
Requires-Dist: more-itertools (==9.0.0)
Requires-Dist: pkginfo (==1.8.3)
Requires-Dist: pycparser (==2.21)
Requires-Dist: Pygments (==2.13.0)
Requires-Dist: pymongo (==4.3.2)
Requires-Dist: python-dotenv (==0.21.0)
Requires-Dist: pytz (==2022.6)
Requires-Dist: readme-renderer (==37.3)
Requires-Dist: requests (==2.28.1)
Requires-Dist: requests-toolbelt (==0.10.1)
Requires-Dist: rfc3986 (==2.0.0)
Requires-Dist: rich (==12.6.0)
Requires-Dist: SecretStorage (==3.3.3)
Requires-Dist: six (==1.16.0)
Requires-Dist: typing-extensions (==4.4.0)
Requires-Dist: urllib3 (==1.26.12)
Requires-Dist: webencodings (==0.5.1)
Requires-Dist: Werkzeug (==2.2.2)
Requires-Dist: zipp (==3.10.0)
